{
    "da915c47ecec16059dd818dbf077159adbd447ca": {
        "timestamp": "2019-12-29T10:07:24",
        "git_size": 576,
        "annex_size": 1945995,
        "total_size": 1946571
    },
    "681a9850c36cb2fb2ccaf5a92ce6768f387ad90a": {
        "timestamp": "2019-12-29T03:28:51",
        "git_size": 576,
        "annex_size": 0,
        "total_size": 576
    },
    "2f1923f34299523f06eea9795c775094ddccd9b2": {
        "timestamp": "2019-12-29T03:28:46",
        "git_size": 458,
        "annex_size": 0,
        "total_size": 458
    },
    "0df2041c7b90c84b27b88195f271fed9436bb63d": {
        "timestamp": "2019-12-29T03:28:41",
        "git_size": 364,
        "annex_size": 0,
        "total_size": 364
    },
    "46c98a4cc957018d4d3184e23d1d3ec98a3055d1": {
        "timestamp": "2019-12-29T03:28:06",
        "git_size": 243,
        "annex_size": 0,
        "total_size": 243
    }
}