{
    "d13ab98f2ded782626dd3413e5901dc732acadf9": {
        "timestamp": "2019-12-25T12:48:32",
        "git_size": 576,
        "annex_size": 2331578,
        "total_size": 2332154
    },
    "36467005c7eb6fcf8016f6d19e99d1e2dea3fcd8": {
        "timestamp": "2019-12-25T05:39:06",
        "git_size": 576,
        "annex_size": 0,
        "total_size": 576
    },
    "554a12f71f7d476a02172128b01908b67591500b": {
        "timestamp": "2019-12-25T05:39:01",
        "git_size": 458,
        "annex_size": 0,
        "total_size": 458
    },
    "9034a9dc26b403a3d54620e86b90ea72ac8be772": {
        "timestamp": "2019-12-25T05:38:58",
        "git_size": 364,
        "annex_size": 0,
        "total_size": 364
    },
    "45ee37c29f0fede8b1598223e8a4294d167a16cd": {
        "timestamp": "2019-12-25T05:38:34",
        "git_size": 243,
        "annex_size": 0,
        "total_size": 243
    }
}