{
    "f8397a6d0efb8da9151d51ba26d8c4d538897436": {
        "timestamp": "2019-12-24T14:26:31",
        "git_size": 576,
        "annex_size": 1697569,
        "total_size": 1698145
    },
    "9850da21229000bba84c8706aeda4c46d1b5f3d3": {
        "timestamp": "2019-12-24T08:11:02",
        "git_size": 576,
        "annex_size": 0,
        "total_size": 576
    },
    "c9f18d9f0c2130953d1937cecc9f655f4e254773": {
        "timestamp": "2019-12-24T08:10:55",
        "git_size": 458,
        "annex_size": 0,
        "total_size": 458
    },
    "5c7a64f726ba33fa763f9f9ac83736e24ab87f83": {
        "timestamp": "2019-12-24T08:10:50",
        "git_size": 364,
        "annex_size": 0,
        "total_size": 364
    },
    "2fefcf559316a69903a35b209642257ebec61f24": {
        "timestamp": "2019-12-24T08:10:17",
        "git_size": 243,
        "annex_size": 0,
        "total_size": 243
    }
}