{
    "56c2192b694a8148775d076f966778406908d17c": {
        "timestamp": "2019-12-21T15:24:45",
        "git_size": 576,
        "annex_size": 2088361,
        "total_size": 2088937
    },
    "e2fc06e4133e8328d10f77a76b2c55b6a76e9102": {
        "timestamp": "2019-12-21T07:37:05",
        "git_size": 576,
        "annex_size": 0,
        "total_size": 576
    },
    "6026a9a5068ecc068f4c71c17232cf4b212d588f": {
        "timestamp": "2019-12-21T07:36:51",
        "git_size": 458,
        "annex_size": 0,
        "total_size": 458
    },
    "40b683b09b88492d7cdd5350dbd2d313eed3f9cd": {
        "timestamp": "2019-12-21T07:36:46",
        "git_size": 364,
        "annex_size": 0,
        "total_size": 364
    },
    "287d2cca93c2a8796dbea47405418afcdcafc742": {
        "timestamp": "2019-12-21T07:36:18",
        "git_size": 243,
        "annex_size": 0,
        "total_size": 243
    }
}