{
    "7d2dce1a718cd1b55d2c058fccc01d618ac8d7c1": {
        "timestamp": "2020-01-17T12:07:08",
        "git_size": 738,
        "annex_size": 2088765,
        "total_size": 2089503
    },
    "cbe88feed63d71f5f990d2ea8d83a2b493782262": {
        "timestamp": "2020-01-17T02:59:32",
        "git_size": 738,
        "annex_size": 0,
        "total_size": 738
    },
    "0109a621e80dd2c90b75f32a78549e7238da8f4f": {
        "timestamp": "2020-01-17T02:59:29",
        "git_size": 603,
        "annex_size": 0,
        "total_size": 603
    },
    "a3728f28a0a2dcb043d22c732da21ce59f53e433": {
        "timestamp": "2020-01-17T02:59:27",
        "git_size": 492,
        "annex_size": 0,
        "total_size": 492
    },
    "c0b06ff17ae003667f31b7ddc9bf14285e108345": {
        "timestamp": "2020-01-17T02:59:24",
        "git_size": 354,
        "annex_size": 0,
        "total_size": 354
    },
    "0e310e9d76ba4d3ecbf9bbd4e4f53cc0b54a0207": {
        "timestamp": "2020-01-17T02:59:18",
        "git_size": 243,
        "annex_size": 0,
        "total_size": 243
    }
}