{
    "8393cff7be8dbab8becbd44ce5673fa55b569dd7": {
        "timestamp": "2020-01-17T12:06:42",
        "git_size": 627,
        "annex_size": 2579779,
        "total_size": 2580406
    },
    "4b8c3bafcd98fba8802c61c511c1eaed162ca886": {
        "timestamp": "2020-01-17T02:59:32",
        "git_size": 627,
        "annex_size": 0,
        "total_size": 627
    },
    "b6dc90bcaacdd1773f603b117b2a2b134a3dde51": {
        "timestamp": "2020-01-17T02:59:30",
        "git_size": 492,
        "annex_size": 0,
        "total_size": 492
    },
    "e0095fb7ce7dfcd131aab9929dd95dcb474b1d03": {
        "timestamp": "2020-01-17T02:59:27",
        "git_size": 381,
        "annex_size": 0,
        "total_size": 381
    },
    "d57c2b9fb8d6d7eaf66cdcc93590e42059c5a943": {
        "timestamp": "2020-01-17T02:59:21",
        "git_size": 243,
        "annex_size": 0,
        "total_size": 243
    }
}