{
    "c9617c1c463dddec7d839a605fbc6703cb75b1f2": {
        "timestamp": "2022-07-01T17:46:43",
        "git_size": 1922512,
        "annex_size": 4681476058,
        "total_size": 4683398570
    },
    "4d933da251e7fb6462c15d2849de8489051a38f6": {
        "timestamp": "2022-07-01T14:53:09",
        "git_size": 1921314,
        "annex_size": 4681477211,
        "total_size": 4683398525
    },
    "8600894cef46b1805689f82bbe1c1629525320aa": {
        "timestamp": "2022-06-30T18:00:30",
        "git_size": 6767976,
        "annex_size": 4676630549,
        "total_size": 4683398525
    },
    "77792f37babef0d3f1ce4a92d1a76739d72132bc": {
        "timestamp": "2022-06-30T17:17:38",
        "git_size": 6767976,
        "annex_size": 4676629396,
        "total_size": 4683397372
    },
    "a34494456fed6301ae5c991ee67ead5fbfea5704": {
        "timestamp": "2022-06-29T18:58:34",
        "git_size": 778760,
        "annex_size": 4682618612,
        "total_size": 4683397372
    },
    "e490f1e69b077987768e0e8c5216c2304c5b7c60": {
        "timestamp": "2022-04-28T21:42:18",
        "git_size": 778766,
        "annex_size": 4681270968,
        "total_size": 4682049734
    },
    "3d5f89d98ae8483e031119bb1bd89be541721710": {
        "timestamp": "2022-04-28T21:41:23",
        "git_size": 779025,
        "annex_size": 4681270968,
        "total_size": 4682049993
    },
    "da01bb1483bcc947e25d8c877be3976166cc80ee": {
        "timestamp": "2022-04-28T21:34:05",
        "git_size": 779025,
        "annex_size": 4692718790,
        "total_size": 4693497815
    },
    "75c4efb5b1b69a17c97d63410eaa5c544dae95ca": {
        "timestamp": "2022-04-28T14:40:22",
        "git_size": 636844,
        "annex_size": 3872705522,
        "total_size": 3873342366
    },
    "39f1bcb1c52943297f4df1933bc85bebc3021bd3": {
        "timestamp": "2022-04-28T14:40:18",
        "git_size": 636844,
        "annex_size": 3872705522,
        "total_size": 3873342366
    },
    "8e06983bcde69c290d6b0499e5b56954e0a92d8e": {
        "timestamp": "2022-04-28T14:35:45",
        "git_size": 636844,
        "annex_size": 3872705522,
        "total_size": 3873342366
    },
    "990034210044587d27cb11eafd4c1361ef410b9c": {
        "timestamp": "2022-04-28T06:26:57",
        "git_size": 636844,
        "annex_size": 3872705522,
        "total_size": 3873342366
    },
    "4ffac29f037a804fdc15e66f077ede345306437b": {
        "timestamp": "2022-04-19T16:08:15",
        "git_size": 636844,
        "annex_size": 3872683156,
        "total_size": 3873320000
    },
    "73944df26597a62d7712bed44a96c5293dc46f76": {
        "timestamp": "2022-04-19T16:08:12",
        "git_size": 636844,
        "annex_size": 3872683156,
        "total_size": 3873320000
    },
    "774e139bbcc46d0dc0585555fd1367c2ec6bac0c": {
        "timestamp": "2022-04-15T20:32:32",
        "git_size": 636844,
        "annex_size": 3872683156,
        "total_size": 3873320000
    },
    "f9be4c63c9ff6dbf7b74fc4402f6eee874fecb0a": {
        "timestamp": "2022-03-04T09:48:54",
        "git_size": 1870,
        "annex_size": 88220,
        "total_size": 90090
    },
    "40741daf5ba8fc1c86fc616ee19e7f3942f1839a": {
        "timestamp": "2022-03-04T04:49:25",
        "git_size": 1507,
        "annex_size": 0,
        "total_size": 1507
    },
    "7a6c4dcabf7dbd9296e24dc5a1314a0a03e63462": {
        "timestamp": "2022-03-04T04:48:21",
        "git_size": 1268,
        "annex_size": 0,
        "total_size": 1268
    },
    "d2e9ba71ec17fc23dcdf294c79b5df96bf5d93a0": {
        "timestamp": "2022-03-04T01:57:13",
        "git_size": 1623,
        "annex_size": 0,
        "total_size": 1623
    },
    "6d7093044624e3ad4fa2b11708e8083d68273428": {
        "timestamp": "2022-03-04T01:57:10",
        "git_size": 1360,
        "annex_size": 0,
        "total_size": 1360
    },
    "a33a4bca0b3b0283190553e510b8c134c5022987": {
        "timestamp": "2022-03-04T01:56:58",
        "git_size": 1115,
        "annex_size": 0,
        "total_size": 1115
    },
    "48bc0f19b2ab9c650b32a65a9d1261c11a726cd4": {
        "timestamp": "2022-03-04T01:56:54",
        "git_size": 941,
        "annex_size": 0,
        "total_size": 941
    },
    "2457b75cecfe40f8e5d12df9df21d937a304a913": {
        "timestamp": "2022-03-04T01:56:48",
        "git_size": 698,
        "annex_size": 0,
        "total_size": 698
    },
    "4a9d0e71a416ca995773ce7e497f6b3289a748cf": {
        "timestamp": "2022-03-04T01:56:45",
        "git_size": 243,
        "annex_size": 0,
        "total_size": 243
    }
}