{
    "f71dbc400bbbfb803e5330ec8673ef77e5909fb7": {
        "timestamp": "2020-05-05T17:47:33",
        "git_size": 11514552,
        "annex_size": 45411449364,
        "total_size": 45422963916
    },
    "b4030afd5659243cc2e050dde91652226c2ed25d": {
        "timestamp": "2020-05-05T17:47:08",
        "git_size": 11514511,
        "annex_size": 45411449364,
        "total_size": 45422963875
    },
    "e76f713ca0b678f7ea566a764d146afdfbb869fe": {
        "timestamp": "2020-04-27T18:59:00",
        "git_size": 11514394,
        "annex_size": 45411449364,
        "total_size": 45422963758
    },
    "d34392a7d235fae88cc6d0362e0e1dac04888ae9": {
        "timestamp": "2020-04-27T18:58:23",
        "git_size": 11514259,
        "annex_size": 45411449364,
        "total_size": 45422963623
    },
    "07196c7767615116d886e0369d832f4762f0b8a5": {
        "timestamp": "2020-04-24T17:42:44",
        "git_size": 11514202,
        "annex_size": 45411449364,
        "total_size": 45422963566
    },
    "2e088f034f84ef96d6fed09581558eb15f01d08d": {
        "timestamp": "2020-04-24T16:48:08",
        "git_size": 472,
        "annex_size": 0,
        "total_size": 472
    },
    "b6342b8e3a0f2d83d51affb7e9860f60f8d5d68b": {
        "timestamp": "2020-04-24T16:48:02",
        "git_size": 243,
        "annex_size": 0,
        "total_size": 243
    }
}