{
    "2cee6d75340a0831d905b5944b150e54418660e1": {
        "timestamp": "2019-10-31T20:45:31",
        "git_size": 1997,
        "annex_size": 134159025,
        "total_size": 134161022
    },
    "c77b8d550904959b7921cbe15f6e93b948f80ca2": {
        "timestamp": "2019-10-31T20:43:58",
        "git_size": 1991,
        "annex_size": 134159025,
        "total_size": 134161016
    },
    "2afbd045688fadcf213fa8752e73373621f49eac": {
        "timestamp": "2019-10-31T20:39:42",
        "git_size": 2200,
        "annex_size": 134159025,
        "total_size": 134161225
    },
    "f605352e67e73c3ff02c58f615544378da48f641": {
        "timestamp": "2019-09-10T00:31:37",
        "git_size": 2212,
        "annex_size": 134159025,
        "total_size": 134161237
    },
    "6207d307f00b9b3444f65d756925d3f37edc3a5e": {
        "timestamp": "2019-09-10T00:30:43",
        "git_size": 2234,
        "annex_size": 134159025,
        "total_size": 134161259
    },
    "500c7af76aedb4bf4ecddf04c4fc9d36af9e5dfc": {
        "timestamp": "2019-09-09T01:20:24",
        "git_size": 2212,
        "annex_size": 134159025,
        "total_size": 134161237
    },
    "662d8977069584eb717283c044b9861c7c030cfe": {
        "timestamp": "2019-09-09T01:19:40",
        "git_size": 2209,
        "annex_size": 134159025,
        "total_size": 134161234
    },
    "9df8c02fd4cd3d4f1d1fa48ab3f4e75ba400b41c": {
        "timestamp": "2019-09-09T01:12:49",
        "git_size": 479,
        "annex_size": 0,
        "total_size": 479
    },
    "3d42ee4f623746295bc2a7fc07103eab1d5aa80e": {
        "timestamp": "2019-09-09T01:12:46",
        "git_size": 250,
        "annex_size": 0,
        "total_size": 250
    },
    "3c4d54623b4ecbc82b44f695ecf202e8350a9b4f": {
        "timestamp": "2019-09-09T01:12:42",
        "git_size": 21,
        "annex_size": 0,
        "total_size": 21
    }
}