{
    "bcb763846faad8ed31e6e85bd39739b67b7a7e5e": {
        "timestamp": "2024-07-31T03:27:04",
        "git_size": 9312209,
        "annex_size": 79520118544,
        "total_size": 79529430753
    },
    "a9de5a3dab2aec8341fcd8673e3260f158f76901": {
        "timestamp": "2024-07-31T03:25:58",
        "git_size": 9312209,
        "annex_size": 79520118544,
        "total_size": 79529430753
    },
    "b2395568553c062b7becac00ee3de945ac9199ed": {
        "timestamp": "2024-07-31T03:24:48",
        "git_size": 9312165,
        "annex_size": 79520118544,
        "total_size": 79529430709
    },
    "1ac4f695e3f6eead2fbb6251b6db9db7d3f87047": {
        "timestamp": "2024-07-31T03:23:26",
        "git_size": 9312165,
        "annex_size": 79520118544,
        "total_size": 79529430709
    },
    "e161b70d4eedd333eced87797696cb45446dc72c": {
        "timestamp": "2024-07-31T03:23:19",
        "git_size": 9312165,
        "annex_size": 79520118544,
        "total_size": 79529430709
    },
    "942766451bffd8028387b445337bcae1ea1bbc10": {
        "timestamp": "2024-07-31T03:20:55",
        "git_size": 9312165,
        "annex_size": 79520118544,
        "total_size": 79529430709
    },
    "bb242325bb1542ae091aaf22659953c7727f7f5d": {
        "timestamp": "2024-07-31T03:17:54",
        "git_size": 9312164,
        "annex_size": 79520118544,
        "total_size": 79529430708
    },
    "2a390684cc1682c16491722bad895ccd84cc13a1": {
        "timestamp": "2024-07-31T03:15:15",
        "git_size": 9312164,
        "annex_size": 79520118544,
        "total_size": 79529430708
    },
    "e8b730ffa36277a8f63073e4dc1cd73940f7a487": {
        "timestamp": "2024-07-31T03:13:51",
        "git_size": 9312164,
        "annex_size": 79520118544,
        "total_size": 79529430708
    },
    "9c751f05f8fac4b139caaf2da3d9e686c21d3fda": {
        "timestamp": "2024-07-31T03:13:09",
        "git_size": 9312164,
        "annex_size": 79520118544,
        "total_size": 79529430708
    },
    "2c3d18ea75659c5aa4b6ed2ef0bfb22ff738b78b": {
        "timestamp": "2024-07-31T03:09:58",
        "git_size": 9312173,
        "annex_size": 79520118544,
        "total_size": 79529430717
    },
    "4c51601e7eb3d6e4570767a4f914b2ec3c14f85e": {
        "timestamp": "2024-07-31T03:05:39",
        "git_size": 9319591,
        "annex_size": 79520118544,
        "total_size": 79529438135
    },
    "528762dff830f40d7936112fb281bbcc25575f06": {
        "timestamp": "2024-07-31T03:03:44",
        "git_size": 9319591,
        "annex_size": 79520118544,
        "total_size": 79529438135
    },
    "d2137c5ddb6aa02dff8036a36cc5625c79cd545c": {
        "timestamp": "2024-07-31T03:02:50",
        "git_size": 9319591,
        "annex_size": 79520118544,
        "total_size": 79529438135
    },
    "3c7992873ec4e9b9ea28c473ec69d890f7ad2fd1": {
        "timestamp": "2024-07-31T03:02:39",
        "git_size": 9319591,
        "annex_size": 79520118544,
        "total_size": 79529438135
    },
    "1e6bfc3ae3ac104cd2ac9599ec02b7534b810b9b": {
        "timestamp": "2024-07-31T03:00:09",
        "git_size": 9312173,
        "annex_size": 79520118544,
        "total_size": 79529430717
    },
    "654939745d6cd8fb1da76ca49f101d3a1610c18b": {
        "timestamp": "2024-07-31T02:58:13",
        "git_size": 9312134,
        "annex_size": 79520118544,
        "total_size": 79529430678
    },
    "53e2ea3f9384d47eb910e30de38b2c7d4db2b899": {
        "timestamp": "2024-07-31T02:54:31",
        "git_size": 9312134,
        "annex_size": 79520118544,
        "total_size": 79529430678
    },
    "510c9b4b5a33cb5ca90ba44a01da21c8dc38b9fc": {
        "timestamp": "2024-07-31T02:53:25",
        "git_size": 9312134,
        "annex_size": 79520118544,
        "total_size": 79529430678
    },
    "202ef9eb0c4e110d90f6531a7a221a28acae3c52": {
        "timestamp": "2024-07-31T02:37:07",
        "git_size": 9312107,
        "annex_size": 79520118544,
        "total_size": 79529430651
    },
    "47bf3d5f90de9a33b70fc95488d58c82142a04cc": {
        "timestamp": "2024-07-31T02:35:11",
        "git_size": 9312085,
        "annex_size": 79520118544,
        "total_size": 79529430629
    },
    "381a5e75b9675bebe44e813a0f2cac313a57a6fa": {
        "timestamp": "2024-07-30T09:36:13",
        "git_size": 9312047,
        "annex_size": 79520118544,
        "total_size": 79529430591
    },
    "1280c7c9e8f08429006330910ecea11c424c8366": {
        "timestamp": "2024-07-30T09:36:12",
        "git_size": 9312047,
        "annex_size": 79520118544,
        "total_size": 79529430591
    },
    "3316b136c1189e90983dad35ab2835c8450810f6": {
        "timestamp": "2024-07-30T09:36:11",
        "git_size": 9312047,
        "annex_size": 79520118544,
        "total_size": 79529430591
    },
    "243cb6f77340d1a4ad3e0037ff6faf9b267a766b": {
        "timestamp": "2024-07-30T09:30:43",
        "git_size": 9312047,
        "annex_size": 79520118544,
        "total_size": 79529430591
    },
    "8ffa614fdc9613a5b653c4c86c14fd43ce486fcf": {
        "timestamp": "2024-07-30T09:30:42",
        "git_size": 9312047,
        "annex_size": 79520118544,
        "total_size": 79529430591
    },
    "4d33fca5cf61e1f85e3effb3883f27074440e3a3": {
        "timestamp": "2024-07-30T09:30:40",
        "git_size": 9312047,
        "annex_size": 79520118544,
        "total_size": 79529430591
    },
    "2028ed212a426e19d6ec913cfc3103e0a2a9c527": {
        "timestamp": "2024-07-30T09:25:14",
        "git_size": 9312047,
        "annex_size": 79520118544,
        "total_size": 79529430591
    },
    "2450ac1ac030aeca1c7ea0db11b8de0d64000056": {
        "timestamp": "2024-07-30T09:23:00",
        "git_size": 9312047,
        "annex_size": 79520118544,
        "total_size": 79529430591
    },
    "11dcf3bcea1ba0834e658526f69c02d3e6b9bfb0": {
        "timestamp": "2024-07-30T07:35:46",
        "git_size": 9311960,
        "annex_size": 79520118544,
        "total_size": 79529430504
    },
    "2af839f746ba7426d415380a99f56b877b86260b": {
        "timestamp": "2024-07-30T07:33:43",
        "git_size": 9311960,
        "annex_size": 79520118544,
        "total_size": 79529430504
    },
    "5b486a8785bd59d90cd10072b86d1a71483d920b": {
        "timestamp": "2024-07-30T06:49:07",
        "git_size": 9311915,
        "annex_size": 79520118544,
        "total_size": 79529430459
    },
    "500b01aa76a4e4cb56869f4880270d8997efc2f0": {
        "timestamp": "2024-07-30T04:04:44",
        "git_size": 490,
        "annex_size": 0,
        "total_size": 490
    }
}